{
    "randomness": {
        "type": "deterministic"
    },
	"condition": {
    "type": "config",
    "config": "Vanilla Sounds:Player",
    "value": true
	},
    "replacements": [
        {
            "matches": "HighAction1:HighAction1",
			"condition": {
			"type": "config",
			"config": "Music:ChaseMusic",
			"value": true
			},
            "sounds": [
                {
                    "sound": "Misc/Silence.ogg"
                }
            ]
        },
        {
            "matches": [
			    "MovementAudio:Aluminum1",
			    "MovementAudio:Aluminum2",
			    "MovementAudio:Aluminum3",
			    "MovementAudio:Aluminum4"
			],
			"condition": {
				"type": "not",
				"condition": {
					"type": "LethalCompany:moon_name",
					"value": "BozorosLevel"
				}
			},
            "sounds": [
                {
                    "sound": "Entities/Player/Aluminum1.ogg",
					"weight": 1
                },
                {
                    "sound": "Entities/Player/Aluminum2.ogg",
					"weight": 1
                },
                {
                    "sound": "Entities/Player/Aluminum3.ogg",
					"weight": 1
                },
                {
                    "sound": "Entities/Player/Aluminum4.ogg",
					"weight": 1
                }
            ]
        },
        {
            "matches": [ 
			    "MovementAudio:Carpet1",
			    "MovementAudio:Carpet2",
			    "MovementAudio:Carpet3",
			    "MovementAudio:Carpet4"
			],
			"condition": {
				"type": "not",
				"condition": {
					"type": "LethalCompany:moon_name",
					"value": "BozorosLevel"
				}
			},
            "sounds": [
                {
                    "sound": "Entities/Player/Carpet1.ogg",
					"weight": 1
                },
                {
                    "sound": "Entities/Player/Carpet2.ogg",
					"weight": 1
                },
                {
                    "sound": "Entities/Player/Carpet3.ogg",
					"weight": 1
                },
                {
                    "sound": "Entities/Player/Carpet4.ogg",
					"weight": 1
                }
            ]
        },
        {
            "matches": [
			    "MovementAudio:Concrete1",
			    "MovementAudio:Concrete2",
			    "MovementAudio:Concrete3",
			    "MovementAudio:Concrete4"
			],
			"condition": {
				"type": "not",
				"condition": {
					"type": "LethalCompany:moon_name",
					"value": "BozorosLevel"
				}
			},
            "sounds": [
                {
                    "sound": "Entities/Player/Concrete1.ogg",
					"weight": 1
                },
                {
                    "sound": "Entities/Player/Concrete2.ogg",
					"weight": 1
                },
                {
                    "sound": "Entities/Player/Concrete3.ogg",
					"weight": 1
                },
                {
                    "sound": "Entities/Player/Concrete4.ogg",
					"weight": 1
                }
            ]
        },
        {
            "matches": [
 			    "MovementAudio:Grass1",
 			    "MovementAudio:Grass2",
 			    "MovementAudio:Grass3",
 			    "MovementAudio:Grass4"
			],
			"condition": {
				"type": "not",
				"condition": {
					"type": "LethalCompany:moon_name",
					"value": "BozorosLevel"
				}
			},
            "sounds": [
                {
                    "sound": "Entities/Player/Grass1.ogg",
					"weight": 1
                },
                {
                    "sound": "Entities/Player/Grass2.ogg",
					"weight": 1
                },
                {
                    "sound": "Entities/Player/Grass3.ogg",
					"weight": 1
                },
                {
                    "sound": "Entities/Player/Grass4.ogg",
					"weight": 1
                }
            ]
        },
        {
            "matches": [
			    "MovementAudio:Gravel1",
			    "MovementAudio:Gravel2",
			    "MovementAudio:Gravel3",
			    "MovementAudio:Gravel4"
			],
			"condition": {
				"type": "not",
				"condition": {
					"type": "LethalCompany:moon_name",
					"value": "BozorosLevel"
				}
			},
            "sounds": [
                {
                    "sound": "Entities/Player/Gravel1.ogg",
					"weight": 1
                },
                {
                    "sound": "Entities/Player/Gravel2.ogg",
					"weight": 1
                },
                {
                    "sound": "Entities/Player/Gravel3.ogg",
					"weight": 1
                },
                {
                    "sound": "Entities/Player/Gravel4.ogg",
					"weight": 1
                }
            ]
        },
        {
            "matches": [
			    "MovementAudio:Gravel1Wet",
			    "MovementAudio:Gravel2Wet",
			    "MovementAudio:Gravel3Wet",
			    "MovementAudio:Gravel4Wet"
			],
			"condition": {
				"type": "not",
				"condition": {
					"type": "LethalCompany:moon_name",
					"value": "BozorosLevel"
				}
			},
            "sounds": [
                {
                    "sound": "Entities/Player/Gravel1Wet.ogg",
					"weight": 1
                },
                {
                    "sound": "Entities/Player/Gravel2Wet.ogg",
					"weight": 1
                },
                {
                    "sound": "Entities/Player/Gravel3Wet.ogg",
					"weight": 1
                },
                {
                    "sound": "Entities/Player/Gravel4Wet.ogg",
					"weight": 1
                }
            ]
        },
        {
            "matches": [
			    "MovementAudio:MetalWalk",
			    "MovementAudio:MetalWalk2",
			    "MovementAudio:MetalWalk3",
			    "MovementAudio:MetalWalk4"
			],
			"condition": {
				"type": "not",
				"condition": {
					"type": "LethalCompany:moon_name",
					"value": "BozorosLevel"
				}
			},
            "sounds": [
                {
                    "sound": "Entities/Player/MetalWalk.ogg",
					"weight": 1
                },
                {
                    "sound": "Entities/Player/MetalWalk2.ogg",
					"weight": 1
                },
                {
                    "sound": "Entities/Player/MetalWalk3.ogg",
					"weight": 1
                },
                {
                    "sound": "Entities/Player/MetalWalk4.ogg",
					"weight": 1
                }
            ]
        },
        {
            "matches": [
			    "MovementAudio:Rock1",
			    "MovementAudio:Rock2",
			    "MovementAudio:Rock3",
			    "MovementAudio:Rock4",
			    "MovementAudio:Rock5"
		    ],
			"condition": {
				"type": "not",
				"condition": {
					"type": "LethalCompany:moon_name",
					"value": "BozorosLevel"
				}
			},
            "sounds": [
                {
                    "sound": "Entities/Player/Rock1.ogg",
					"weight": 1
                },
                {
                    "sound": "Entities/Player/Rock2.ogg",
					"weight": 1
                },
                {
                    "sound": "Entities/Player/Rock3.ogg",
					"weight": 1
                },
                {
                    "sound": "Entities/Player/Rock4.ogg",
					"weight": 1
                },
                {
                    "sound": "Entities/Player/Rock5.ogg",
					"weight": 1
                }
            ]
        },
        {
            "matches": [
			    "MovementAudio:Snow1",
			    "MovementAudio:Snow2",
			    "MovementAudio:Snow3",
			    "MovementAudio:Snow4"
		    ],
			"condition": {
				"type": "not",
				"condition": {
					"type": "LethalCompany:moon_name",
					"value": "BozorosLevel"
				}
			},
            "sounds": [
                {
                    "sound": "Entities/Player/Snow1.ogg",
					"weight": 1
                },
                {
                    "sound": "Entities/Player/Snow2.ogg",
					"weight": 1
                },
                {
                    "sound": "Entities/Player/Snow3.ogg",
					"weight": 1
                },
                {
                    "sound": "Entities/Player/Snow4.ogg",
					"weight": 1
                }
            ]
        },
        {
            "matches": [
			    "MovementAudio:Tile1",
			    "MovementAudio:Tile2",
			    "MovementAudio:Tile3",
			    "MovementAudio:Tile4",
			    "MovementAudio:Tile5"
			],
			"condition": {
				"type": "not",
				"condition": {
					"type": "LethalCompany:moon_name",
					"value": "BozorosLevel"
				}
			},
            "sounds": [
                {
                    "sound": "Entities/Player/Tile1.ogg",
					"weight": 1
                },
                {
                    "sound": "Entities/Player/Tile2.ogg",
					"weight": 1
                },
                {
                    "sound": "Entities/Player/Tile3.ogg",
					"weight": 1
                },
                {
                    "sound": "Entities/Player/Tile4.ogg",
					"weight": 1
                },
                {
                    "sound": "Entities/Player/Tile5.ogg",
					"weight": 1
                }
            ]
        },
        {
            "matches": [
			    "MovementAudio:WoodStep1",
			    "MovementAudio:WoodStep2",
			    "MovementAudio:WoodStep3",
			    "MovementAudio:WoodStep4"
			],
			"condition": {
				"type": "not",
				"condition": {
					"type": "LethalCompany:moon_name",
					"value": "BozorosLevel"
				}
			},
            "sounds": [
                {
                    "sound": "Entities/Player/WoodStep1.ogg",
					"weight": 1
                },
                {
                    "sound": "Entities/Player/WoodStep2.ogg",
					"weight": 1
                },
                {
                    "sound": "Entities/Player/WoodStep3.ogg",
					"weight": 1
                },
                {
                    "sound": "Entities/Player/WoodStep4.ogg",
					"weight": 1
                }
            ]
        },
        {
            "matches": [
			    "MovementAudio:WoodB1",
			    "MovementAudio:WoodB2",
			    "MovementAudio:WoodB3",
			    "MovementAudio:WoodB4",
			    "MovementAudio:WoodB5",
			    "MovementAudio:WoodB6",
			    "MovementAudio:WoodB7"
			],
			"condition": {
				"type": "not",
				"condition": {
					"type": "LethalCompany:moon_name",
					"value": "BozorosLevel"
				}
			},
            "sounds": [
                {
                    "sound": "Entities/Player/WoodStep1.ogg",
					"weight": 1
                },
                {
                    "sound": "Entities/Player/WoodStep2.ogg",
					"weight": 1
                },
                {
                    "sound": "Entities/Player/WoodStep3.ogg",
					"weight": 1
                },
                {
                    "sound": "Entities/Player/WoodStep4.ogg",
					"weight": 1
                }
            ]
        },
        {
            "matches": [
			    "MovementAudio:Aluminum1",
			    "MovementAudio:Aluminum2",
			    "MovementAudio:Aluminum3",
			    "MovementAudio:Aluminum4"
			],
			"condition": {
			"type": "and",
			"conditions": [
					{
						"type": "LethalCompany:moon_name",
						"value": "BozorosLevel"
					},
					{
						"type": "config",
						"config": "Mods:CompatibilityBozoros",
						"value": true
					},
				]
			},
            "sounds": [
                {
                    "sound": "Entities/ClownAluminum1.ogg",
					"weight": 1
                },
                {
                    "sound": "Entities/ClownAluminum2.ogg",
					"weight": 1
                },
                {
                    "sound": "Entities/ClownAluminum3.ogg",
					"weight": 1
                },
                {
                    "sound": "Entities/ClownAluminum4.ogg",
					"weight": 1
                }
            ]
        },
        {
            "matches": [ 
			    "MovementAudio:Carpet1",
			    "MovementAudio:Carpet2",
			    "MovementAudio:Carpet3",
			    "MovementAudio:Carpet4"
			],
			"condition": {
			"type": "and",
			"conditions": [
					{
						"type": "LethalCompany:moon_name",
						"value": "BozorosLevel"
					},
					{
						"type": "config",
						"config": "Mods:CompatibilityBozoros",
						"value": true
					},
				]
			},
            "sounds": [
                {
                    "sound": "Entities/ClownCarpet1.ogg",
					"weight": 1
                },
                {
                    "sound": "Entities/ClownCarpet2.ogg",
					"weight": 1
                },
                {
                    "sound": "Entities/ClownCarpet3.ogg",
					"weight": 1
                },
                {
                    "sound": "Entities/ClownCarpet4.ogg",
					"weight": 1
                }
            ]
        },
        {
            "matches": [
			    "MovementAudio:Concrete1",
			    "MovementAudio:Concrete2",
			    "MovementAudio:Concrete3",
			    "MovementAudio:Concrete4"
			],
			"condition": {
			"type": "and",
			"conditions": [
					{
						"type": "LethalCompany:moon_name",
						"value": "BozorosLevel"
					},
					{
						"type": "config",
						"config": "Mods:CompatibilityBozoros",
						"value": true
					},
				]
			},
            "sounds": [
                {
                    "sound": "Entities/ClownConcrete1.ogg",
					"weight": 1
                },
                {
                    "sound": "Entities/ClownConcrete2.ogg",
					"weight": 1
                },
                {
                    "sound": "Entities/ClownConcrete3.ogg",
					"weight": 1
                },
                {
                    "sound": "Entities/ClownConcrete4.ogg",
					"weight": 1
                }
            ]
        },
        {
            "matches": [
 			    "MovementAudio:Grass1",
 			    "MovementAudio:Grass2",
 			    "MovementAudio:Grass3",
 			    "MovementAudio:Grass4"
			],
			"condition": {
			"type": "and",
			"conditions": [
					{
						"type": "LethalCompany:moon_name",
						"value": "BozorosLevel"
					},
					{
						"type": "config",
						"config": "Mods:CompatibilityBozoros",
						"value": true
					},
				]
			},
            "sounds": [
                {
                    "sound": "Entities/ClownGrass1.ogg",
					"weight": 1
                },
                {
                    "sound": "Entities/ClownGrass2.ogg",
					"weight": 1
                },
                {
                    "sound": "Entities/ClownGrass3.ogg",
					"weight": 1
                },
                {
                    "sound": "Entities/ClownGrass4.ogg",
					"weight": 1
                }
            ]
        },
        {
            "matches": [
			    "MovementAudio:Gravel1",
			    "MovementAudio:Gravel2",
			    "MovementAudio:Gravel3",
			    "MovementAudio:Gravel4"
			],
			"condition": {
			"type": "and",
			"conditions": [
					{
						"type": "LethalCompany:moon_name",
						"value": "BozorosLevel"
					},
					{
						"type": "config",
						"config": "Mods:CompatibilityBozoros",
						"value": true
					},
				]
			},
            "sounds": [
                {
                    "sound": "Entities/ClownGravel1.ogg",
					"weight": 1
                },
                {
                    "sound": "Entities/ClownGravel2.ogg",
					"weight": 1
                },
                {
                    "sound": "Entities/ClownGravel3.ogg",
					"weight": 1
                },
                {
                    "sound": "Entities/ClownGravel4.ogg",
					"weight": 1
                }
            ]
        },
        {
            "matches": [
			    "MovementAudio:Gravel1Wet",
			    "MovementAudio:Gravel2Wet",
			    "MovementAudio:Gravel3Wet",
			    "MovementAudio:Gravel4Wet"
			],
			"condition": {
			"type": "and",
			"conditions": [
					{
						"type": "LethalCompany:moon_name",
						"value": "BozorosLevel"
					},
					{
						"type": "config",
						"config": "Mods:CompatibilityBozoros",
						"value": true
					},
				]
			},
            "sounds": [
                {
                    "sound": "Entities/ClownGravel1Wet.ogg",
					"weight": 1
                },
                {
                    "sound": "Entities/ClownGravel2Wet.ogg",
					"weight": 1
                },
                {
                    "sound": "Entities/ClownGravel3Wet.ogg",
					"weight": 1
                },
                {
                    "sound": "Entities/ClownGravel4Wet.ogg",
					"weight": 1
                }
            ]
        },
        {
            "matches": [
			    "MovementAudio:MetalWalk",
			    "MovementAudio:MetalWalk2",
			    "MovementAudio:MetalWalk3",
			    "MovementAudio:MetalWalk4"
			],
			"condition": {
			"type": "and",
			"conditions": [
					{
						"type": "LethalCompany:moon_name",
						"value": "BozorosLevel"
					},
					{
						"type": "config",
						"config": "Mods:CompatibilityBozoros",
						"value": true
					},
				]
			},
            "sounds": [
                {
                    "sound": "Entities/ClownMetalWalk.ogg",
					"weight": 1
                },
                {
                    "sound": "Entities/ClownMetalWalk2.ogg",
					"weight": 1
                },
                {
                    "sound": "Entities/ClownMetalWalk3.ogg",
					"weight": 1
                },
                {
                    "sound": "Entities/ClownMetalWalk4.ogg",
					"weight": 1
                }
            ]
        },
        {
            "matches": [
			    "MovementAudio:Rock1",
			    "MovementAudio:Rock2",
			    "MovementAudio:Rock3",
			    "MovementAudio:Rock4",
			    "MovementAudio:Rock5"
		    ],
			"condition": {
			"type": "and",
			"conditions": [
					{
						"type": "LethalCompany:moon_name",
						"value": "BozorosLevel"
					},
					{
						"type": "config",
						"config": "Mods:CompatibilityBozoros",
						"value": true
					},
				]
			},
            "sounds": [
                {
                    "sound": "Entities/ClownRock1.ogg",
					"weight": 1
                },
                {
                    "sound": "Entities/ClownRock2.ogg",
					"weight": 1
                },
                {
                    "sound": "Entities/ClownRock3.ogg",
					"weight": 1
                },
                {
                    "sound": "Entities/ClownRock4.ogg",
					"weight": 1
                },
                {
                    "sound": "Entities/ClownRock5.ogg",
					"weight": 1
                }
            ]
        },
        {
            "matches": [
			    "MovementAudio:Snow1",
			    "MovementAudio:Snow2",
			    "MovementAudio:Snow3",
			    "MovementAudio:Snow4"
		    ],
			"condition": {
			"type": "and",
			"conditions": [
					{
						"type": "LethalCompany:moon_name",
						"value": "BozorosLevel"
					},
					{
						"type": "config",
						"config": "Mods:CompatibilityBozoros",
						"value": true
					},
				]
			},
            "sounds": [
                {
                    "sound": "Entities/ClownSnow1.ogg",
					"weight": 1
                },
                {
                    "sound": "Entities/ClownSnow2.ogg",
					"weight": 1
                },
                {
                    "sound": "Entities/ClownSnow3.ogg",
					"weight": 1
                },
                {
                    "sound": "Entities/ClownSnow4.ogg",
					"weight": 1
                }
            ]
        },
        {
            "matches": [
			    "MovementAudio:Tile1",
			    "MovementAudio:Tile2",
			    "MovementAudio:Tile3",
			    "MovementAudio:Tile4",
			    "MovementAudio:Tile5"
			],
			"condition": {
			"type": "and",
			"conditions": [
					{
						"type": "LethalCompany:moon_name",
						"value": "BozorosLevel"
					},
					{
						"type": "config",
						"config": "Mods:CompatibilityBozoros",
						"value": true
					},
				]
			},
            "sounds": [
                {
                    "sound": "Entities/ClownTile1.ogg",
					"weight": 1
                },
                {
                    "sound": "Entities/ClownTile2.ogg",
					"weight": 1
                },
                {
                    "sound": "Entities/ClownTile3.ogg",
					"weight": 1
                },
                {
                    "sound": "Entities/ClownTile4.ogg",
					"weight": 1
                },
                {
                    "sound": "Entities/ClownTile5.ogg",
					"weight": 1
                }
            ]
        },
        {
            "matches": [
			    "MovementAudio:WoodStep1",
			    "MovementAudio:WoodStep2",
			    "MovementAudio:WoodStep3",
			    "MovementAudio:WoodStep4"
			],
			"condition": {
			"type": "and",
			"conditions": [
					{
						"type": "LethalCompany:moon_name",
						"value": "BozorosLevel"
					},
					{
						"type": "config",
						"config": "Mods:CompatibilityBozoros",
						"value": true
					},
				]
			},
            "sounds": [
                {
                    "sound": "Entities/ClownWoodStep1.ogg",
					"weight": 1
                },
                {
                    "sound": "Entities/ClownWoodStep2.ogg",
					"weight": 1
                },
                {
                    "sound": "Entities/ClownWoodStep3.ogg",
					"weight": 1
                },
                {
                    "sound": "Entities/ClownWoodStep4.ogg",
					"weight": 1
                }
            ]
        },
        {
            "matches": [
			    "MovementAudio:WoodB1",
			    "MovementAudio:WoodB2",
			    "MovementAudio:WoodB3",
			    "MovementAudio:WoodB4",
			    "MovementAudio:WoodB5",
			    "MovementAudio:WoodB6",
			    "MovementAudio:WoodB7"
			],
			"condition": {
			"type": "and",
			"conditions": [
					{
						"type": "LethalCompany:moon_name",
						"value": "BozorosLevel"
					},
					{
						"type": "config",
						"config": "Mods:CompatibilityBozoros",
						"value": true
					},
				]
			},
            "sounds": [
                {
                    "sound": "Entities/ClownWoodStep1.ogg",
					"weight": 1
                },
                {
                    "sound": "Entities/ClownWoodStep2.ogg",
					"weight": 1
                },
                {
                    "sound": "Entities/ClownWoodStep3.ogg",
					"weight": 1
                },
                {
                    "sound": "Entities/ClownWoodStep4.ogg",
					"weight": 1
                }
            ]
        },
        {
            "matches": [
			"*:DieFromFallDamageSFX1",
			"*:CrushGore"
			],
	        "condition": {
            "type": "config",
            "config": "Vanilla Sounds:PlayerDeath",
            "value": true
	        },
            "sounds": [
                {
                    "sound": "Entities/Player/DieFromFallDamageSFX1-Blyat.ogg",
					"weight": 1
                },
                {
                    "sound": "Entities/Player/DieFromFallDamageSFX1-Caleb.ogg",
					"weight": 1
                },
                {
                    "sound": "Entities/Player/DieFromFallDamageSFX1-CJ.ogg",
					"weight": 1
                },
                {
                    "sound": "Entities/Player/DieFromFallDamageSFX1-CSGO.ogg",
					"weight": 1
                },
                {
                    "sound": "Entities/Player/DieFromFallDamageSFX1-Doge.ogg",
					"weight": 1
                },
                {
                    "sound": "Entities/Player/DieFromFallDamageSFX1-Fan.ogg",
					"weight": 1
                },
                {
                    "sound": "Entities/Player/DieFromFallDamageSFX1-Fort.ogg",
					"weight": 1
                },
                {
                    "sound": "Entities/Player/DieFromFallDamageSFX1-GTA.ogg",
					"weight": 1
                },
                {
                    "sound": "Entities/Player/DieFromFallDamageSFX1-HL.ogg",
					"weight": 1
                },
                {
                    "sound": "Entities/Player/DieFromFallDamageSFX1-kidow.ogg",
					"weight": 1
                },
                {
                    "sound": "Entities/Player/DieFromFallDamageSFX1-oof.ogg",
					"weight": 1
                },
                {
                    "sound": "Entities/Player/DieFromFallDamageSFX1-owch.ogg",
					"weight": 1
                },
                {
                    "sound": "Entities/Player/DieFromFallDamageSFX1-PeloLaugh.ogg",
					"weight": 1
                },
                {
                    "sound": "Entities/Player/DieFromFallDamageSFX1-PeloScream.ogg",
					"weight": 1
                },
                {
                    "sound": "Entities/Player/DieFromFallDamageSFX1-PeloScream2.ogg",
					"weight": 1
                },
                {
                    "sound": "Entities/Player/DieFromFallDamageSFX1-Steve.ogg",
					"weight": 1
                },
                {
                    "sound": "Entities/Player/DieFromFallDamageSFX1-TF2.ogg",
					"weight": 1
                },
                {
                    "sound": "Entities/Player/DieFromFallDamageSFX1-Toad.ogg",
					"weight": 1
                },
                {
                    "sound": "Entities/Player/DieFromFallDamageSFX1-Tom.ogg",
					"weight": 1
                },
                {
                    "sound": "Entities/Player/DieFromFallDamageSFX1-Undertale.ogg",
					"weight": 1
                }
            ]
        },
        {
            "matches": "UIAudio:AlertHUD",
            "sounds": [
                {
                    "sound": "Entities/Player/ApparatusRemoveAlert.ogg"
                }
            ]
        },
        {
            "matches": "UIAudio:CollectScrapSmall",
            "sounds": [
                {
                    "sound": "Entities/Player/CollectScrapSmall.ogg"
                }
            ]
        },
        {
            "matches": "UIAudio:CounterAdd",
            "sounds": [
                {
                    "sound": "Entities/Player/CounterAdd.ogg"
                }
            ]
        },
        {
            "matches": "UIAudio:CounterAddFinish",
            "sounds": [
                {
                    "sound": "Entities/Player/CounterAddFinish.ogg"
                }
            ]
        },
        {
            "matches": "UIAudio:CriticalInjury",
            "sounds": [
                {
                    "sound": "Entities/Player/CriticalInjury.ogg"
                }
            ]
        },
        {
            "matches": "UIAudio:DaysLeftSFX",
            "sounds": [
                {
                    "sound": "Entities/Player/DaysLeftSFX.ogg"
                }
            ]
        },
        {
            "matches": "UIAudio:FinalDayBeforeDeadline",
            "sounds": [
                {
                    "sound": "Entities/Player/FinalDayBeforeDeadline.ogg"
                }
            ]
        },
        {
            "matches": "UIAudio:GlobalNotificationSFX",
            "sounds": [
                {
                    "sound": "Entities/Player/GlobalNotificationSFX.ogg"
                }
            ]
        },
        {
            "matches": "UIAudio:HUDSystemAlert",
            "sounds": [
                {
                    "sound": "Entities/Player/HUDSystemAlert.ogg"
                }
            ]
        },
        {
            "matches": "UnderwaterAudio:BreathingUnderwater",
            "sounds": [
                {
                    "sound": "Entities/Player/BreathingUnderwater.ogg"
                }
            ]
        },
        {
            "matches": "UnderwaterBubblesAudio:TalkingUnderwaterBubbles",
            "sounds": [
                {
                    "sound": "Entities/Player/TalkingUnderwaterBubbles.ogg"
                }
            ]
        },
        {
            "matches": [
			"OxygenDefault:Inhale_1",
			"OxygenDefault:Inhale_2"
			],
            "sounds": [
                {
                    "sound": "Compatibility/OxygenCalm1.ogg",
					"weight": 1
                },
                {
                    "sound": "Compatibility/OxygenCalm2.ogg",
					"weight": 1
                },
                {
                    "sound": "Compatibility/OxygenCalm3.ogg",
					"weight": 1
                }
            ]
        },
        {
            "matches": "OxygenDefault:heavy_Inhale_1",
            "sounds": [
                {
                    "sound": "Compatibility/OxygenFast1.ogg",
					"weight": 1
                },
                {
                    "sound": "Compatibility/OxygenFast2.ogg",
					"weight": 1
                },
                {
                    "sound": "Compatibility/OxygenFast3.ogg",
					"weight": 1
                }
            ]
        },
        {
            "matches": "UIAudio:ReachedQuotaSFX",
            "sounds": [
                {
                    "sound": "Entities/Player/ReachedQuotaSFX-rare.ogg",
					"weight": 1
                },
                {
                    "sound": "Entities/Player/ReachedQuotaSFX-common.ogg",
					"weight": 9
                }
            ]
        },
        {
            "matches": "*:LevelDown",
            "sounds": [
                {
                    "sound": "Entities/Player/UILevelDown.ogg"
                }
            ]
        },
        {
            "matches": "*:LevelUp",
            "sounds": [
                {
                    "sound": "Entities/Player/UILevelUp.ogg"
                }
            ]
        },
        {
            "matches": "UIAudio:Scan",
            "sounds": [
                {
                    "sound": "Entities/Player/Scan-var1.ogg",
					"weight": 1
                },
                {
                    "sound": "Entities/Player/Scan-var2.ogg",
					"weight": 1
                },
                {
                    "sound": "Entities/Player/Scan-var3.ogg",
					"weight": 1
                }
            ]
        },
        {
            "matches": [
			    "UIAudio:TipsHUD",
				"UIAudio:TipsHUD2"
			],
            "sounds": [
                {
                    "sound": "Entities/Player/TipsHUD.ogg",
					"weight": 1
                },
                {
                    "sound": "Entities/Player/TipsHUD1.ogg",
					"weight": 1
                },
                {
                    "sound": "Entities/Player/TipsHUD2.ogg",
					"weight": 1
                }
            ]
        },
        {
            "matches": [
			    "UIAudio:WarningHUD",
			    "UIAudio:WarningHUD2",
			    "UIAudio:WarningHUD3"
			],
            "sounds": [
                {
                    "sound": "Entities/Player/WarningHUD.ogg",
					"weight": 1
                },
                {
                    "sound": "Entities/Player/WarningHUD2.ogg",
					"weight": 1
                },
                {
                    "sound": "Entities/Player/WarningHUD3.ogg",
					"weight": 1
                }
            ]
        },
        {
            "matches": [
			    "UIAudio:ComputerBeep1",
			    "UIAudio:ComputerBeep2",
			    "UIAudio:ComputerBeep3",
			    "UIAudio:ComputerBeep4",
			    "UIAudio:ComputerBeep5",
			    "UIAudio:ComputerBeep6"
			],
            "sounds": [
                {
                    "sound": "Entities/Player/HUDBeep1.ogg",
					"weight": 1
                },
                {
                    "sound": "Entities/Player/HUDBeep2.ogg",
					"weight": 1
                },
                {
                    "sound": "Entities/Player/HUDBeep3.ogg",
					"weight": 1
                },
                {
                    "sound": "Entities/Player/HUDBeep4.ogg",
					"weight": 1
                },
                {
                    "sound": "Entities/Player/HUDBeep5.ogg",
					"weight": 1
                },
                {
                    "sound": "Entities/Player/HUDBeep6.ogg",
					"weight": 1
                },
                {
                    "sound": "Entities/Player/HUDBeep7.ogg",
					"weight": 1
                }
            ]
        },
        {
            "matches": "UIAudio:TakeDamage",
            "sounds": [
                {
                    "sound": "Entities/Player/TakeDamage-var1.ogg",
					"weight": 1
                },
                {
                    "sound": "Entities/Player/TakeDamage-var2.ogg",
					"weight": 1
                },
                {
                    "sound": "Entities/Player/TakeDamage-var3.ogg",
					"weight": 1
                }
            ]
        },
        {
            "matches": "*:HitPlayerSFX",
            "sounds": [
                {
                    "sound": "Entities/Player/ShovelHitPlayer.ogg"
                }
            ]
        },
        {
            "matches": [
			    "WebHangerPhysics:BodyCollision1",
				"WebHangerPhysics:BodyCollision2",
				"WebHangerPhysics:BodyCollision3"
			],
            "sounds": [
                {
                    "sound": "Entities/Player/BodyCollision1.ogg",
					"weight": 1
                },
                {
                    "sound": "Entities/Player/BodyCollision2.ogg",
					"weight": 1
                },
                {
                    "sound": "Entities/Player/BodyCollision3.ogg",
					"weight": 1
                }
            ]
        },
        {
            "matches": "EarsRingingAudio:EarsRinging",
            "sounds": [
                {
                    "sound": "Entities/Player/EarsRinging-common.ogg",
					"weight": 15
                },
                {
                    "sound": "Entities/Player/EarsRinging-rare.ogg",
					"weight": 1
                }
            ]
        },
        {
            "matches": [
			    "MovementAudio:JumpHitGround1",
				"MovementAudio:JumpHitGround2"
			],
            "sounds": [
                {
                    "sound": "Entities/Player/JumpHitGround-var1.ogg",
					"weight": 1
                },
                {
                    "sound": "Entities/Player/JumpHitGround-var2.ogg",
					"weight": 1
                },
                {
                    "sound": "Entities/Player/JumpHitGround-var3.ogg",
					"weight": 1
                },
                {
                    "sound": "Entities/Player/JumpHitGround-var4.ogg",
					"weight": 1
                }
            ]
        },
        {
            "matches": "StatusEffectAudio:SinkIntoMud",
            "sounds": [
                {
                    "sound": "Entities/Player/SinkIntoMud.ogg"
                }
            ]
        },
        {
            "matches": "MovementAudio:StartJump",
            "sounds": [
                {
                    "sound": "Entities/Player/StartJump-prkr.ogg",
					"weight": 1
                },
                {
                    "sound": "Entities/Player/StartJump-var1.ogg",
					"weight": 40
                },
                {
                    "sound": "Entities/Player/StartJump-var2.ogg",
					"weight": 40
                }
            ]
        }
    ]
}